pyroar/__init__.py
pyroar/clientfactory.py
pyroar/commons.py
pyroar/configclient.py
pyroar/pokeclient.py
pyroar-1.0.0.dist-info/DESCRIPTION.rst
pyroar-1.0.0.dist-info/METADATA
pyroar-1.0.0.dist-info/RECORD
pyroar-1.0.0.dist-info/WHEEL
pyroar-1.0.0.dist-info/metadata.json
pyroar-1.0.0.dist-info/top_level.txt
