Metadata-Version: 2.0
Name: pyroar
Version: 1.0.0
Summary: Python client for PokeAPI
Home-page: https://github.com/dapregi/pyroar
Author: Daniel Perez-Gil
Author-email: dperezgil89@gmail.com
License: UNKNOWN
Platform: UNKNOWN
Requires: pyyaml
